{
  "realm": "myrealm",
  "enabled": true,

  "clients": [
    {
      "clientId": "frontend-client",
      "enabled": true,
      "protocol": "openid-connect",
      "publicClient": true,
      "redirectUris": ["http://localhost:3000/*"],
      "authorizationServicesEnabled": true
    },
    {
      "clientId": "backend-client",
      "enabled": true,
      "protocol": "openid-connect",
      "publicClient": false,
      "directAccessGrantsEnabled": true
    },
    {
      "clientId": "traefik-client",
      "enabled": true,
      "protocol": "openid-connect",
      "publicClient": false,
      "secret": "qjSYmYdxSVYtALpaTK7LEzShzw2qPJ0R",
      "redirectUris": [
        "http://users.localhost/oidc/callback"
      ],
      "webOrigins": [
        "http://users.localhost"
      ],
      "serviceAccountsEnabled": true,
      "directAccessGrantsEnabled": false,
      "standardFlowEnabled": true,
      "implicitFlowEnabled": false
    }
  ],

  "roles": {
    "realm": [
      { "name": "admin" },
      { "name": "manager" },
      { "name": "employee" }
    ]
  },

  "users": [
    {
      "username": "john",
      "enabled": true,
      "email": "john@company.com",
      "credentials": [
        { "type": "password", "value": "JohnPass123" }
      ],
      "realmRoles": ["employee"]
    },
    {
      "username": "alice",
      "enabled": true,
      "email": "alice@company.com",
      "credentials": [
        { "type": "password", "value": "AlicePass123" }
      ],
      "realmRoles": ["manager"]
    }
  ]
}
